rotatepdf/__init__.py
rotatepdf/rotatepdf.py
rotatepdf-2025.3.25.dist-info/licenses/LICENSE
rotatepdf-2025.3.25.dist-info/METADATA
rotatepdf-2025.3.25.dist-info/WHEEL
rotatepdf-2025.3.25.dist-info/entry_points.txt
rotatepdf-2025.3.25.dist-info/top_level.txt
rotatepdf-2025.3.25.dist-info/RECORD
