Metadata-Version: 2.4
Name: rotatepdf
Version: 2025.3.25
Summary: Rotate PDF easily from command line
Author: Andre Miras
Project-URL: Homepage, https://github.com/AndreMiras/rotatepdf
Requires-Python: >=3.9
License-File: LICENSE
Requires-Dist: PyPDF2<3
Provides-Extra: dev
Requires-Dist: pytest; extra == "dev"
Requires-Dist: pytest-cov; extra == "dev"
Requires-Dist: ruff; extra == "dev"
Requires-Dist: tox; extra == "dev"
Dynamic: license-file
